_rl_accel.abi3.so
rl_accel-0.9.1.dist-info/WHEEL
rl_accel-0.9.1.dist-info/top_level.txt
rl_accel-0.9.1.dist-info/LICENSE.txt
rl_accel-0.9.1.dist-info/METADATA
rl_accel-0.9.1.dist-info/RECORD
